{"http://www.imdb.com/title/tt0017536/": {"Title": "Western Pluck", "Year": "1926", "Rating": null, "Votes": null, "Metascore": null, "Gross": null, "Genre": "Western", "Certificate": null, "Runtime": null, "Director": "Travers Vale", "Star1": "Art Acord", "Star1_URL": "http://www.imdb.com/name/nm0010134/?ref_=adv_li_st_0", "Star2": "Marceline Day", "Star2_URL": "http://www.imdb.com/name/nm0206496/?ref_=adv_li_st_1", "Star3": "Ray Ripley", "Star3_URL": "http://www.imdb.com/name/nm0728019/?ref_=adv_li_st_2", "Star4": "Robert Rose", "Star4_URL": "http://www.imdb.com/name/nm0741638/?ref_=adv_li_st_3"}, "http://www.imdb.com/title/tt0015578/": {"Title": "The Arizona Romeo", "Year": "1925", "Rating": null, "Votes": null, "Metascore": null, "Gross": null, "Genre": "Comedy, Western", "Certificate": null, "Runtime": "50 min", "Director": "Edmund Mortimer", "Star1": "Buck Jones", "Star1_URL": "http://www.imdb.com/name/nm0427659/?ref_=adv_li_st_0", "Star2": "Lucy Fox", "Star2_URL": "http://www.imdb.com/name/nm0289127/?ref_=adv_li_st_1", "Star3": "Bud Geary", "Star3_URL": "http://www.imdb.com/name/nm0311274/?ref_=adv_li_st_2", "Star4": "Thomas R. Mills", "Star4_URL": "http://www.imdb.com/name/nm0590205/?ref_=adv_li_st_3"}, "http://www.imdb.com/title/tt3959542/": {"Title": "1870 Texas", "Year": "2014", "Rating": null, "Votes": null, "Metascore": null, "Gross": null, "Genre": "Action, Adventure, Western", "Certificate": null, "Runtime": "77 min", "Director": "William Booth", "Star1": "Lance Eakright", "Star1_URL": "http://www.imdb.com/name/nm3460984/?ref_=adv_li_st_0", "Star2": "Bob Fanucchi", "Star2_URL": "http://www.imdb.com/name/nm2294324/?ref_=adv_li_st_1", "Star3": "Greg Ingram", "Star3_URL": "http://www.imdb.com/name/nm1862555/?ref_=adv_li_st_2", "Star4": "Dennis O'Neill", "Star4_URL": "http://www.imdb.com/name/nm0642138/?ref_=adv_li_st_3"}, "http://www.imdb.com/title/tt0019196/": {"Title": "The Mystery Rider", "Year": "1928", "Rating": null, "Votes": null, "Metascore": null, "Gross": null, "Genre": "Western", "Certificate": null, "Runtime": null, "Director": "Robert J. Horner", "Star1": "William Desmond", "Star1_URL": "http://www.imdb.com/name/nm0221488/?ref_=adv_li_st_0", "Star2": "Derelys Perdue", "Star2_URL": "http://www.imdb.com/name/nm0672971/?ref_=adv_li_st_1", "Star3": "Tom London", "Star3_URL": "http://www.imdb.com/name/nm0163417/?ref_=adv_li_st_2", "Star4": "Bud Osborne", "Star4_URL": "http://www.imdb.com/name/nm0651627/?ref_=adv_li_st_3"}, "http://www.imdb.com/title/tt0132961/": {"Title": "Flash o' Lightning", "Year": "1925", "Rating": null, "Votes": null, "Metascore": null, "Gross": null, "Genre": "Western", "Certificate": null, "Runtime": null, "Director": "Leo D. Maloney", "Star1": "Leo D. Maloney", "Star1_URL": "http://www.imdb.com/name/nm0540575/?ref_=adv_li_st_0", "Star2": "Josephine Hill", "Star2_URL": "http://www.imdb.com/name/nm0384420/?ref_=adv_li_st_1", "Star3": "Eva Thatcher", "Star3_URL": "http://www.imdb.com/name/nm0857118/?ref_=adv_li_st_2", "Star4": "Whitehorse", "Star4_URL": "http://www.imdb.com/name/nm0925750/?ref_=adv_li_st_3"}, "http://www.imdb.com/title/tt7909340/": {"Title": "Witness", "Year": "2018", "Rating": null, "Votes": null, "Metascore": null, "Gross": null, "Genre": "Western", "Certificate": null, "Runtime": "67 min", "Director": "Aykan Yucel Irwins", "Star1": "Trudy Allen", "Star1_URL": "http://www.imdb.com/name/nm5653078/?ref_=adv_li_st_0", "Star2": "Debbie Arney", "Star2_URL": "http://www.imdb.com/name/nm9574132/?ref_=adv_li_st_1", "Star3": "John Belesky", "Star3_URL": "http://www.imdb.com/name/nm9574139/?ref_=adv_li_st_2", "Star4": "Meisy Chia", "Star4_URL": "http://www.imdb.com/name/nm9574143/?ref_=adv_li_st_3"}}